<sajdas>
<sajda index="1" sura="7" aya="206" type="recommended"/>
<sajda index="2" sura="13" aya="15" type="recommended"/>
<sajda index="3" sura="16" aya="50" type="recommended"/>
<sajda index="4" sura="17" aya="109" type="recommended"/>
<sajda index="5" sura="19" aya="58" type="recommended"/>
<sajda index="6" sura="22" aya="18" type="recommended"/>
<sajda index="7" sura="22" aya="77" type="recommended"/>
<sajda index="8" sura="25" aya="60" type="recommended"/>
<sajda index="9" sura="27" aya="26" type="recommended"/>
<sajda index="10" sura="32" aya="15" type="obligatory"/>
<sajda index="11" sura="38" aya="24" type="recommended"/>
<sajda index="12" sura="41" aya="38" type="obligatory"/>
<sajda index="13" sura="53" aya="62" type="obligatory"/>
<sajda index="14" sura="84" aya="21" type="recommended"/>
<sajda index="15" sura="96" aya="19" type="obligatory"/>
</sajdas>